progress_session/__init__.py
progress_session/__version__.py
progress_session/custom_logging.py
progress_session/example.py
progress_session/progress_session.py
progress_session-0.30.4.dist-info/METADATA
progress_session-0.30.4.dist-info/WHEEL
progress_session-0.30.4.dist-info/top_level.txt
progress_session-0.30.4.dist-info/RECORD
